td_ameritrade_api/__init__.py
td_ameritrade_api/accounts.py
td_ameritrade_api/auth.py
td_ameritrade_api/data.py
td_ameritrade_api/errors.py
td_ameritrade_api/helpers.py
td_ameritrade_api/td_client.py
td_ameritrade_api/trading.py
td_ameritrade_api/watchlist.py
td_ameritrade_api-1.0.4.dist-info/LICENSE
td_ameritrade_api-1.0.4.dist-info/METADATA
td_ameritrade_api-1.0.4.dist-info/WHEEL
td_ameritrade_api-1.0.4.dist-info/top_level.txt
td_ameritrade_api-1.0.4.dist-info/RECORD
