Metadata-Version: 2.1
Name: td-ameritrade-api
Version: 1.0.4
Summary: A python wrapper for the TD ameritrade API
Home-page: https://github.com/jacobvm04/td-ameritrade-api
Author: Jacob Van Meter
Author-email: jacobvm04@gmail.com
License: UNKNOWN
Platform: UNKNOWN
Classifier: Programming Language :: Python :: 3
Classifier: License :: OSI Approved :: MIT License
Classifier: Operating System :: OS Independent
Requires-Python: >=3.6
